healthyurl.py
healthyurl-0.1.1.dist-info/entry_points.txt
healthyurl-0.1.1.dist-info/WHEEL
healthyurl-0.1.1.dist-info/METADATA
healthyurl-0.1.1.dist-info/RECORD
