Metadata-Version: 2.1
Name: healthyurl
Version: 0.1.1
Summary: A lightweight command-line tool for performing HTTP health checks using Python's standard library. Exits with code 1 on HTTP errors.
Author-email: Martín Gaitán <gaitan@gmail.com>
Requires-Python: >=3.8
Requires-Dist: pytest ; extra == "test"
Requires-Dist: pytest-mock ; extra == "test"
Project-URL: Home, https://github.com/mgaitan/healthyurl
Provides-Extra: test
